football/__init__.py
football/admin.py
football/apilol.py
football/apps.py
football/models.py
football/tests.py
football/urls.py
football/views.py
football/migrations/__init__.py
football_boardi/__init__.py
football_boardi/asgi.py
football_boardi/settings.py
football_boardi/urls.py
football_boardi/wsgi.py
EPL_data_boardxx-0.0.3.dist-info/LICENSE
EPL_data_boardxx-0.0.3.dist-info/METADATA
EPL_data_boardxx-0.0.3.dist-info/WHEEL
EPL_data_boardxx-0.0.3.dist-info/top_level.txt
EPL_data_boardxx-0.0.3.dist-info/RECORD
