Metadata-Version: 2.1
Name: EPL-data-boardxx
Version: 0.0.3
Summary: Pthon Wrapper
Home-page: https://github.com/Kshitiz-Mhto/EPL-data-board
Author: Ibceberg
Author-email: ibergx00@gmail.com
License: https://www.apache.org/licenses/LICENSE-2.0
Classifier: License :: OSI Approved :: Apache Software License
Classifier: Programming Language :: Python :: 3.5
Classifier: Programming Language :: Python :: 3.6
Classifier: Programming Language :: Python :: 3.7
Requires-Python: >=3.5
License-File: LICENSE
